clloader/__init__.py
clloader/loader.py
clloader/viz.py
clloader/datasets/__init__.py
clloader/datasets/base.py
clloader/datasets/fellowship.py
clloader/datasets/imagenet.py
clloader/datasets/pytorch.py
clloader/datasets/transformed.py
tests/__init__.py
tests/test_imagefolder.py
tests/test_inmemory.py
tests/test_transformed.py
continnum-0.0.1.dist-info/LICENSE
continnum-0.0.1.dist-info/METADATA
continnum-0.0.1.dist-info/WHEEL
continnum-0.0.1.dist-info/top_level.txt
continnum-0.0.1.dist-info/RECORD
