Metadata-Version: 2.1
Name: continnum
Version: 0.0.1
Summary: A DataLoader library for Continual Learning in PyTorch.
Home-page: https://github.com/arthurdouillard/continual_loader
Author: Arthur Douillard
Author-email: ar.douillard@gmail.com
License: UNKNOWN
Platform: UNKNOWN
Classifier: Programming Language :: Python :: 3
Classifier: License :: OSI Approved :: MIT License
Classifier: Operating System :: OS Independent
Requires-Python: >=3.6
